lasagne/__init__.py
lasagne/conftest.py
lasagne/init.py
lasagne/nonlinearities.py
lasagne/objectives.py
lasagne/random.py
lasagne/regularization.py
lasagne/updates.py
lasagne/utils.py
lasagne/layers/__init__.py
lasagne/layers/base.py
lasagne/layers/conv.py
lasagne/layers/corrmm.py
lasagne/layers/cuda_convnet.py
lasagne/layers/dense.py
lasagne/layers/dnn.py
lasagne/layers/embedding.py
lasagne/layers/helper.py
lasagne/layers/input.py
lasagne/layers/local.py
lasagne/layers/merge.py
lasagne/layers/noise.py
lasagne/layers/normalization.py
lasagne/layers/pool.py
lasagne/layers/recurrent.py
lasagne/layers/shape.py
lasagne/layers/special.py
lasagne/theano_extensions/__init__.py
lasagne/theano_extensions/conv.py
lasagne/theano_extensions/padding.py
wbia_cnn/__init__.py
wbia_cnn/__main__.py
wbia_cnn/_plugin.py
wbia_cnn/_plugin_grabmodels.py
wbia_cnn/_version.py
wbia_cnn/augment.py
wbia_cnn/batch_processing.py
wbia_cnn/custom_layers.py
wbia_cnn/dataset.py
wbia_cnn/draw_net.py
wbia_cnn/draw_results.py
wbia_cnn/experiments.py
wbia_cnn/harness.py
wbia_cnn/ingest_data.py
wbia_cnn/ingest_helpers.py
wbia_cnn/ingest_wbia.py
wbia_cnn/lasagne_ext.py
wbia_cnn/net_strs.py
wbia_cnn/netrun.py
wbia_cnn/process.py
wbia_cnn/sandbox.py
wbia_cnn/test.py
wbia_cnn/theano_ext.py
wbia_cnn/utils.py
wbia_cnn/models/__init__.py
wbia_cnn/models/_model_legacy.py
wbia_cnn/models/abstract_models.py
wbia_cnn/models/aoi.py
wbia_cnn/models/aoi2.py
wbia_cnn/models/background.py
wbia_cnn/models/classifier.py
wbia_cnn/models/classifier2.py
wbia_cnn/models/dummy.py
wbia_cnn/models/labeler.py
wbia_cnn/models/mnist.py
wbia_cnn/models/pretrained.py
wbia_cnn/models/quality.py
wbia_cnn/models/siam.py
wbia_cnn/models/viewpoint.py
wbia_cnn-4.0.0.dist-info/LICENSE
wbia_cnn-4.0.0.dist-info/METADATA
wbia_cnn-4.0.0.dist-info/WHEEL
wbia_cnn-4.0.0.dist-info/top_level.txt
wbia_cnn-4.0.0.dist-info/RECORD
