Metadata-Version: 2.1
Name: wbia-cnn
Version: 4.0.0
Summary: WBIA CNN - Convolutional Neural Network (CNN) plug-in for WBIA
Home-page: https://github.com/WildbookOrg/wbia-plugin-cnn
Author: Jon Crall, Jason Parham, WildMe Developers
Author-email: dev@wildme.org
License: BSD
Platform: UNKNOWN
Classifier: Development Status :: 6 - Mature
Classifier: License :: OSI Approved :: BSD License
Classifier: Intended Audience :: Developers
Classifier: Intended Audience :: Science/Research
Classifier: Operating System :: MacOS :: MacOS X
Classifier: Operating System :: Unix
Classifier: Topic :: Software Development :: Libraries :: Python Modules
Classifier: Topic :: Utilities
Classifier: Programming Language :: Python :: 3
Classifier: Programming Language :: Python :: 3.5
Classifier: Programming Language :: Python :: 3.6
Classifier: Programming Language :: Python :: 3.7
Classifier: Programming Language :: Python :: 3.8
License-File: LICENSE
Requires-Dist: scikit-learn
Requires-Dist: theano
Requires-Dist: wbia-utool
Requires-Dist: wbia-vtool
Requires-Dist: wildbook-ia
Provides-Extra: all
Requires-Dist: cmake ; extra == 'all'
Requires-Dist: ninja ; extra == 'all'
Requires-Dist: scikit-build ; extra == 'all'
Requires-Dist: setuptools ; extra == 'all'
Requires-Dist: setuptools-scm[toml] ; extra == 'all'
Requires-Dist: wheel ; extra == 'all'
Requires-Dist: scikit-learn ; extra == 'all'
Requires-Dist: theano ; extra == 'all'
Requires-Dist: wbia-utool ; extra == 'all'
Requires-Dist: wbia-vtool ; extra == 'all'
Requires-Dist: wildbook-ia ; extra == 'all'
Requires-Dist: brunette ; extra == 'all'
Requires-Dist: codecov ; extra == 'all'
Requires-Dist: coverage ; extra == 'all'
Requires-Dist: pytest ; extra == 'all'
Requires-Dist: pytest-cov ; extra == 'all'
Requires-Dist: xdoctest ; extra == 'all'
Provides-Extra: build
Requires-Dist: cmake ; extra == 'build'
Requires-Dist: ninja ; extra == 'build'
Requires-Dist: scikit-build ; extra == 'build'
Requires-Dist: setuptools ; extra == 'build'
Requires-Dist: setuptools-scm[toml] ; extra == 'build'
Requires-Dist: wheel ; extra == 'build'
Provides-Extra: runtime
Requires-Dist: scikit-learn ; extra == 'runtime'
Requires-Dist: theano ; extra == 'runtime'
Requires-Dist: wbia-utool ; extra == 'runtime'
Requires-Dist: wbia-vtool ; extra == 'runtime'
Requires-Dist: wildbook-ia ; extra == 'runtime'
Provides-Extra: tests
Requires-Dist: brunette ; extra == 'tests'
Requires-Dist: codecov ; extra == 'tests'
Requires-Dist: coverage ; extra == 'tests'
Requires-Dist: pytest ; extra == 'tests'
Requires-Dist: pytest-cov ; extra == 'tests'
Requires-Dist: xdoctest ; extra == 'tests'
